core/__init__.py
core/client.py
core/config.py
core/exceptions.py
core/server.py
core/types.py
core/utils.py
main.py
prompts/__init__.py
tools/__init__.py
tools/info_tools.py
tools/task_tools.py
tools/video_tools.py
mcp_luma-2026.1.25.0.dist-info/METADATA
mcp_luma-2026.1.25.0.dist-info/WHEEL
mcp_luma-2026.1.25.0.dist-info/entry_points.txt
mcp_luma-2026.1.25.0.dist-info/licenses/LICENSE
mcp_luma-2026.1.25.0.dist-info/RECORD
