Metadata-Version: 2.3
Name: mcp-luma
Version: 2026.1.25.0
Summary: MCP Server for Luma AI Video Generation via AceDataCloud API
Project-URL: Homepage, https://github.com/AceDataCloud/mcp-luma
Project-URL: Documentation, https://platform.acedata.cloud/documents/5bd3597d-1ff8-44ad-a580-b66b48393e7f
Project-URL: Repository, https://github.com/AceDataCloud/mcp-luma
Project-URL: Issues, https://github.com/AceDataCloud/mcp-luma/issues
Project-URL: Changelog, https://github.com/AceDataCloud/mcp-luma/blob/main/CHANGELOG.md
Author-email: AceDataCloud <support@acedata.cloud>
Maintainer-email: AceDataCloud <support@acedata.cloud>
License: MIT
License-File: LICENSE
Keywords: acedata,ai,claude,dream-machine,generation,llm,luma,mcp,model-context-protocol,video
Classifier: Development Status :: 4 - Beta
Classifier: Intended Audience :: Developers
Classifier: License :: OSI Approved :: MIT License
Classifier: Operating System :: OS Independent
Classifier: Programming Language :: Python :: 3
Classifier: Programming Language :: Python :: 3.10
Classifier: Programming Language :: Python :: 3.11
Classifier: Programming Language :: Python :: 3.12
Classifier: Topic :: Multimedia :: Video
Classifier: Topic :: Scientific/Engineering :: Artificial Intelligence
Requires-Python: >=3.10
Requires-Dist: httpx>=0.27.0
Requires-Dist: loguru>=0.7.0
Requires-Dist: mcp>=1.2.0
Requires-Dist: pydantic>=2.0.0
Requires-Dist: python-dotenv>=1.0.0
Provides-Extra: all
Requires-Dist: build>=1.2.0; extra == 'all'
Requires-Dist: mypy>=1.10.0; extra == 'all'
Requires-Dist: pre-commit>=3.7.0; extra == 'all'
Requires-Dist: pytest-asyncio>=0.23.0; extra == 'all'
Requires-Dist: pytest-cov>=5.0.0; extra == 'all'
Requires-Dist: pytest>=8.0.0; extra == 'all'
Requires-Dist: respx>=0.21.0; extra == 'all'
Requires-Dist: ruff>=0.4.0; extra == 'all'
Requires-Dist: twine>=5.0.0; extra == 'all'
Provides-Extra: dev
Requires-Dist: mypy>=1.10.0; extra == 'dev'
Requires-Dist: pre-commit>=3.7.0; extra == 'dev'
Requires-Dist: ruff>=0.4.0; extra == 'dev'
Provides-Extra: release
Requires-Dist: build>=1.2.0; extra == 'release'
Requires-Dist: twine>=5.0.0; extra == 'release'
Provides-Extra: test
Requires-Dist: pytest-asyncio>=0.23.0; extra == 'test'
Requires-Dist: pytest-cov>=5.0.0; extra == 'test'
Requires-Dist: pytest>=8.0.0; extra == 'test'
Requires-Dist: respx>=0.21.0; extra == 'test'
